{"type":"FeatureCollection","features":[{"type":"Feature","properties":{"Name":"School French American Charter School","Type":"Charter School"},"geometry":{"type":"Point","coordinates":[-122.697429,38.441557]}},{"type":"Feature","properties":{"Name":"Charter School for the Arts","Type":"Charter School"},"geometry":{"type":"Point","coordinates":[-122.71436,38.447234]},"id":1},{"type":"Feature","properties":{"Name":"Cesar Chavez Language Academy","Type":"Charter School"},"geometry":{"type":"Point","coordinates":[-122.745752,38.425864]}},{"type":"Feature","properties":{"Name":"Santa Rosa Accelerated Charter School","Type":"Charter School"},"geometry":{"coordinates":[-122.67025783834478,38.481417849931006],"type":"Point"},"id":21}]}